<?xml version="1.0" encoding="utf-8" ?>
<dwsync>
<file name="Carousel_Placeholder.png" server="u446730.ssh.masterhost.ru" local="130868830418059117" remote="130867803600000000" Dst="0" />
<file name="image-23-07-15-03-06-12.jpg" server="u446730.ssh.masterhost.ru" local="130868830594449202" remote="130867881000000000" Dst="0" />
<file name="image-23-07-15-03-06-13.jpg" server="u446730.ssh.masterhost.ru" local="130868830599809507" remote="130867881000000000" Dst="0" />
<file name="image-23-07-15-03-06-14.jpg" server="u446730.ssh.masterhost.ru" local="130868830601049578" remote="130867881000000000" Dst="0" />
<file name="image-23-07-15-03-06-15 (1).jpg" server="u446730.ssh.masterhost.ru" local="130868830438870300" remote="130867881000000000" Dst="0" />
<file name="image-23-07-15-03-06-15.jpg" server="u446730.ssh.masterhost.ru" local="130868830609150042" remote="130867881000000000" Dst="0" />
<file name="image-23-07-15-03-06-4.jpg" server="u446730.ssh.masterhost.ru" local="130868830611690183" remote="130867881000000000" Dst="0" />
<file name="image-23-07-15-03-06-9.jpg" server="u446730.ssh.masterhost.ru" local="130868830634471494" remote="130867881000000000" Dst="0" />
<file name="ImgResponsive_Placeholder.png" server="u446730.ssh.masterhost.ru" local="130868830463451709" remote="130867803600000000" Dst="0" />
<file name="image-23-07-15-03-06-8.jpg" server="u446730.ssh.masterhost.ru" local="130868830616880483" remote="130867881000000000" Dst="0" />
<file name="Thumbnail_Placeholder.png" server="u446730.ssh.masterhost.ru" local="130868830466671885" remote="130867803600000000" Dst="0" />
</dwsync>